bblean/__init__.py
bblean/_config.py
bblean/_console.py
bblean/_cpp_similarity.cp311-win_amd64.pyd
bblean/_memory.py
bblean/_merges.py
bblean/_py_similarity.py
bblean/_timer.py
bblean/_version.py
bblean/analysis.py
bblean/bitbirch.py
bblean/cli.py
bblean/fingerprints.py
bblean/metrics.py
bblean/multiround.py
bblean/plotting.py
bblean/similarity.py
bblean/sklearn.py
bblean/smiles.py
bblean/utils.py
bblean/_legacy/__init__.py
bblean/_legacy/bb_int64.py
bblean/_legacy/bb_uint8.py
bblean/csrc/README.md
bblean/csrc/similarity.cpp
bblean-0.8.1.dist-info/licenses/LICENSE
bblean-0.8.1.dist-info/METADATA
bblean-0.8.1.dist-info/WHEEL
bblean-0.8.1.dist-info/entry_points.txt
bblean-0.8.1.dist-info/top_level.txt
bblean-0.8.1.dist-info/RECORD
