Metadata-Version: 2.4
Name: bblean
Version: 0.8.1
Summary: BitBirch-Lean Python package
Author: The Miranda-Quintana Lab and other BitBirch developers
Author-email: Ramon Alain Miranda Quintana <quintana@chem.ufl.edu>, Krisztina Zsigmond <kzsigmond@ufl.edu>, Ignacio Pickering <ipickering@ufl.edu>, Kenneth Lopez Perez <klopezperez@chem.ufl.edu>, Miroslav Lzicar <miroslav.lzicar@deepmedchem.com>
License-Expression: GPL-3.0-only
Project-URL: homepage, https://github.com/mqcomplab/bblean.git
Project-URL: repository, https://github.com/mqcomplab/bblean.git
Project-URL: documentation, https://github.com/mqcomplab/bblean.git
Classifier: Intended Audience :: Science/Research
Classifier: Intended Audience :: Developers
Classifier: Programming Language :: Python
Classifier: Topic :: Software Development
Classifier: Topic :: Scientific/Engineering
Classifier: Development Status :: 4 - Beta
Classifier: Operating System :: POSIX
Classifier: Operating System :: Unix
Classifier: Operating System :: MacOS
Classifier: Programming Language :: Python :: 3
Classifier: Programming Language :: Python :: 3.11
Classifier: Programming Language :: Python :: 3.12
Classifier: Programming Language :: Python :: 3.13
Classifier: Programming Language :: Python :: Implementation :: CPython
Requires-Python: >=3.11
License-File: LICENSE
Requires-Dist: scipy
Requires-Dist: rdkit
Requires-Dist: numpy>=2.0
Requires-Dist: pandas
Requires-Dist: psutil
Requires-Dist: matplotlib
Requires-Dist: colorcet
Requires-Dist: seaborn
Requires-Dist: scikit-learn
Requires-Dist: rich
Requires-Dist: typer
Requires-Dist: opentsne
Requires-Dist: umap-learn
Requires-Dist: pynndescent
Dynamic: license-file
